{
  "formatVersion": 1,
  "database": {
    "version": 2,
    "identityHash": "b47c638ad62463311f8c3540150fbff5",
    "entities": [
      {
        "tableName": "identity_table",
        "createSql": "CREATE TABLE IF NOT EXISTS `${TABLE_NAME}` (`id` INTEGER PRIMARY KEY AUTOINCREMENT NOT NULL, `name` TEXT NOT NULL, `status` TEXT NOT NULL, `detail` TEXT, `code_uri` TEXT NOT NULL, `next_account_number` INTEGER NOT NULL, `identity_provider` TEXT NOT NULL, `identity_object` TEXT, `private_id_object_data_encrypted` TEXT NOT NULL)",
        "fields": [
          {
            "fieldPath": "id",
            "columnName": "id",
            "affinity": "INTEGER",
            "notNull": true
          },
          {
            "fieldPath": "name",
            "columnName": "name",
            "affinity": "TEXT",
            "notNull": true
          },
          {
            "fieldPath": "status",
            "columnName": "status",
            "affinity": "TEXT",
            "notNull": true
          },
          {
            "fieldPath": "detail",
            "columnName": "detail",
            "affinity": "TEXT",
            "notNull": false
          },
          {
            "fieldPath": "codeUri",
            "columnName": "code_uri",
            "affinity": "TEXT",
            "notNull": true
          },
          {
            "fieldPath": "nextAccountNumber",
            "columnName": "next_account_number",
            "affinity": "INTEGER",
            "notNull": true
          },
          {
            "fieldPath": "identityProvider",
            "columnName": "identity_provider",
            "affinity": "TEXT",
            "notNull": true
          },
          {
            "fieldPath": "identityObject",
            "columnName": "identity_object",
            "affinity": "TEXT",
            "notNull": false
          },
          {
            "fieldPath": "privateIdObjectDataEncrypted",
            "columnName": "private_id_object_data_encrypted",
            "affinity": "TEXT",
            "notNull": true
          }
        ],
        "primaryKey": {
          "columnNames": [
            "id"
          ],
          "autoGenerate": true
        },
        "indices": [],
        "foreignKeys": []
      },
      {
        "tableName": "account_table",
        "createSql": "CREATE TABLE IF NOT EXISTS `${TABLE_NAME}` (`id` INTEGER PRIMARY KEY AUTOINCREMENT NOT NULL, `identity_id` INTEGER NOT NULL, `name` TEXT NOT NULL, `address` TEXT NOT NULL, `submission_id` TEXT NOT NULL, `transaction_status` INTEGER NOT NULL, `encrypted_account_data` TEXT NOT NULL, `revealed_attributes` TEXT NOT NULL, `credential` TEXT NOT NULL, `finalized_balance` INTEGER NOT NULL, `current_balance` INTEGER NOT NULL, `total_balance` INTEGER NOT NULL, `total_unshielded_balance` INTEGER NOT NULL, `total_shielded_balance` INTEGER NOT NULL, `finalized_encrypted_balance` TEXT, `current_encrypted_balance` TEXT, `current_balance_status` INTEGER NOT NULL)",
        "fields": [
          {
            "fieldPath": "id",
            "columnName": "id",
            "affinity": "INTEGER",
            "notNull": true
          },
          {
            "fieldPath": "identityId",
            "columnName": "identity_id",
            "affinity": "INTEGER",
            "notNull": true
          },
          {
            "fieldPath": "name",
            "columnName": "name",
            "affinity": "TEXT",
            "notNull": true
          },
          {
            "fieldPath": "address",
            "columnName": "address",
            "affinity": "TEXT",
            "notNull": true
          },
          {
            "fieldPath": "submissionId",
            "columnName": "submission_id",
            "affinity": "TEXT",
            "notNull": true
          },
          {
            "fieldPath": "transactionStatus",
            "columnName": "transaction_status",
            "affinity": "INTEGER",
            "notNull": true
          },
          {
            "fieldPath": "encryptedAccountData",
            "columnName": "encrypted_account_data",
            "affinity": "TEXT",
            "notNull": true
          },
          {
            "fieldPath": "revealedAttributes",
            "columnName": "revealed_attributes",
            "affinity": "TEXT",
            "notNull": true
          },
          {
            "fieldPath": "credential",
            "columnName": "credential",
            "affinity": "TEXT",
            "notNull": true
          },
          {
            "fieldPath": "finalizedBalance",
            "columnName": "finalized_balance",
            "affinity": "INTEGER",
            "notNull": true
          },
          {
            "fieldPath": "currentBalance",
            "columnName": "current_balance",
            "affinity": "INTEGER",
            "notNull": true
          },
          {
            "fieldPath": "totalBalance",
            "columnName": "total_balance",
            "affinity": "INTEGER",
            "notNull": true
          },
          {
            "fieldPath": "totalUnshieldedBalance",
            "columnName": "total_unshielded_balance",
            "affinity": "INTEGER",
            "notNull": true
          },
          {
            "fieldPath": "totalShieldedBalance",
            "columnName": "total_shielded_balance",
            "affinity": "INTEGER",
            "notNull": true
          },
          {
            "fieldPath": "finalizedEncryptedBalance",
            "columnName": "finalized_encrypted_balance",
            "affinity": "TEXT",
            "notNull": false
          },
          {
            "fieldPath": "currentEncryptedBalance",
            "columnName": "current_encrypted_balance",
            "affinity": "TEXT",
            "notNull": false
          },
          {
            "fieldPath": "encryptedBalanceStatus",
            "columnName": "current_balance_status",
            "affinity": "INTEGER",
            "notNull": true
          }
        ],
        "primaryKey": {
          "columnNames": [
            "id"
          ],
          "autoGenerate": true
        },
        "indices": [],
        "foreignKeys": []
      },
      {
        "tableName": "transfer_table",
        "createSql": "CREATE TABLE IF NOT EXISTS `${TABLE_NAME}` (`id` INTEGER PRIMARY KEY AUTOINCREMENT NOT NULL, `account_id` INTEGER NOT NULL, `amount` INTEGER NOT NULL, `cost` INTEGER NOT NULL, `from_address` TEXT NOT NULL, `to_address` TEXT NOT NULL, `expiry` INTEGER NOT NULL, `created_at` INTEGER NOT NULL, `submission_id` TEXT NOT NULL, `transaction_status` INTEGER NOT NULL, `outcome` INTEGER NOT NULL, `transactionType` TEXT NOT NULL, `newSelfEncryptedAmount` TEXT, `newStartIndex` INTEGER NOT NULL, `nonce` TEXT)",
        "fields": [
          {
            "fieldPath": "id",
            "columnName": "id",
            "affinity": "INTEGER",
            "notNull": true
          },
          {
            "fieldPath": "accountId",
            "columnName": "account_id",
            "affinity": "INTEGER",
            "notNull": true
          },
          {
            "fieldPath": "amount",
            "columnName": "amount",
            "affinity": "INTEGER",
            "notNull": true
          },
          {
            "fieldPath": "cost",
            "columnName": "cost",
            "affinity": "INTEGER",
            "notNull": true
          },
          {
            "fieldPath": "fromAddress",
            "columnName": "from_address",
            "affinity": "TEXT",
            "notNull": true
          },
          {
            "fieldPath": "toAddress",
            "columnName": "to_address",
            "affinity": "TEXT",
            "notNull": true
          },
          {
            "fieldPath": "expiry",
            "columnName": "expiry",
            "affinity": "INTEGER",
            "notNull": true
          },
          {
            "fieldPath": "createdAt",
            "columnName": "created_at",
            "affinity": "INTEGER",
            "notNull": true
          },
          {
            "fieldPath": "submissionId",
            "columnName": "submission_id",
            "affinity": "TEXT",
            "notNull": true
          },
          {
            "fieldPath": "transactionStatus",
            "columnName": "transaction_status",
            "affinity": "INTEGER",
            "notNull": true
          },
          {
            "fieldPath": "outcome",
            "columnName": "outcome",
            "affinity": "INTEGER",
            "notNull": true
          },
          {
            "fieldPath": "transactionType",
            "columnName": "transactionType",
            "affinity": "TEXT",
            "notNull": true
          },
          {
            "fieldPath": "newSelfEncryptedAmount",
            "columnName": "newSelfEncryptedAmount",
            "affinity": "TEXT",
            "notNull": false
          },
          {
            "fieldPath": "newStartIndex",
            "columnName": "newStartIndex",
            "affinity": "INTEGER",
            "notNull": true
          },
          {
            "fieldPath": "nonce",
            "columnName": "nonce",
            "affinity": "TEXT",
            "notNull": false
          }
        ],
        "primaryKey": {
          "columnNames": [
            "id"
          ],
          "autoGenerate": true
        },
        "indices": [],
        "foreignKeys": []
      },
      {
        "tableName": "recipient_table",
        "createSql": "CREATE TABLE IF NOT EXISTS `${TABLE_NAME}` (`id` INTEGER PRIMARY KEY AUTOINCREMENT NOT NULL, `name` TEXT NOT NULL, `address` TEXT NOT NULL)",
        "fields": [
          {
            "fieldPath": "id",
            "columnName": "id",
            "affinity": "INTEGER",
            "notNull": true
          },
          {
            "fieldPath": "name",
            "columnName": "name",
            "affinity": "TEXT",
            "notNull": true
          },
          {
            "fieldPath": "address",
            "columnName": "address",
            "affinity": "TEXT",
            "notNull": true
          }
        ],
        "primaryKey": {
          "columnNames": [
            "id"
          ],
          "autoGenerate": true
        },
        "indices": [],
        "foreignKeys": []
      },
      {
        "tableName": "encrypted_amount_table",
        "createSql": "CREATE TABLE IF NOT EXISTS `${TABLE_NAME}` (`encryptedkey` TEXT NOT NULL, `amount` TEXT, PRIMARY KEY(`encryptedkey`))",
        "fields": [
          {
            "fieldPath": "encryptedkey",
            "columnName": "encryptedkey",
            "affinity": "TEXT",
            "notNull": true
          },
          {
            "fieldPath": "amount",
            "columnName": "amount",
            "affinity": "TEXT",
            "notNull": false
          }
        ],
        "primaryKey": {
          "columnNames": [
            "encryptedkey"
          ],
          "autoGenerate": false
        },
        "indices": [],
        "foreignKeys": []
      }
    ],
    "views": [],
    "setupQueries": [
      "CREATE TABLE IF NOT EXISTS room_master_table (id INTEGER PRIMARY KEY,identity_hash TEXT)",
      "INSERT OR REPLACE INTO room_master_table (id,identity_hash) VALUES(42, 'b47c638ad62463311f8c3540150fbff5')"
    ]
  }
}